meh_logging/__init__.py
meh_logging/logger.py
meh_logging/enums/levels.py
meh_logging/formatters/__init__.py
meh_logging/formatters/json.py
meh_logging/transports/__init__.py
meh_logging/transports/stream.py
meh_logging/utils/__init__.py
meh_logging/utils/package.py
meh_logging/utils/read_package.py
meh_logging-1.0.4.dist-info/LICENSE
meh_logging-1.0.4.dist-info/METADATA
meh_logging-1.0.4.dist-info/WHEEL
meh_logging-1.0.4.dist-info/top_level.txt
meh_logging-1.0.4.dist-info/RECORD
