Metadata-Version: 2.1
Name: meh-logging
Version: 1.0.4
Summary: Custom logging package for MEH projects.
Author-email: Jim de Ronde <jim.de.ronde@greenhousegroup.com>
Project-URL: Homepage, https://gitlab.com/GreenhouseGroup/meh/meh-logging-python
Project-URL: Bug Tracker, https://gitlab.com/GreenhouseGroup/meh/meh-logging-python/-/issues
Classifier: Programming Language :: Python :: 3
Classifier: License :: OSI Approved :: MIT License
Classifier: Operating System :: OS Independent
Requires-Python: >=3.8
License-File: LICENSE
